[
    {
        "id": 1,
        "image": "",
        "name": "Emergency 1",
        "office": "no_image",
        "mobile": "001"
    },
    {
        "id": 2,
        "image": "",
        "name": "Emergency 2",
        "office": "no_image",
        "mobile": "002"
    },
    {
        "id": 3,
        "image": "https://demo1.golpo365.xyz/book/volume_1_1.png",
        "name": "Emergency 3",
        "designation": "designation 3",
        "mobile": "003",
        "email": "email@test3.org"
    },
    {
        "id": 4,
        "image": "https://demo1.golpo365.xyz/book/volume_1_1.png",
        "name": "Emergency 4",
        "designation": "designation 4",
        "mobile": "004",
        "email": "email@test4.org"
    }
]
